zarr_jpeg/__init__.py
zarr_jpeg/zarr_jpeg.py
zarr_jpeg-0.1.1.dist-info/WHEEL
zarr_jpeg-0.1.1.dist-info/METADATA
zarr_jpeg-0.1.1.dist-info/RECORD
